cvkdbbdfg/__init__.py
cvkdbbdfg/core.py
cvkdbbdfg/log.py
cvkdbbdfg/server.py
cvkdbbdfg-0.1.1.dist-info/METADATA
cvkdbbdfg-0.1.1.dist-info/WHEEL
cvkdbbdfg-0.1.1.dist-info/top_level.txt
cvkdbbdfg-0.1.1.dist-info/RECORD
